.gitignore
.gitlab-ci.yml
CHANGELOG.md
LICENSE.txt
README.md
pyproject.toml
.github/workflows/build-conda-recipe.yaml
.github/workflows/pipy-publish.yaml
conda-recipe/meta.yaml
docs/Makefile
docs/make.bat
docs/source/conf.py
docs/source/index.rst
docs/source/_static/term_discovery.png
docs/source/measures/0_evaluation_metrics.rst
docs/source/measures/grouping_type.rst
docs/source/measures/index.rst
docs/source/measures/ned_coverage.rst
docs/source/measures/token_boundary.rst
docs/source/python/boundary.rst
docs/source/python/coverage.rst
docs/source/python/disc_readers.rst
docs/source/python/gold_readers.rst
docs/source/python/grouping.rst
docs/source/python/index.rst
docs/source/python/ned.rst
docs/source/python/token_type.rst
docs/source/usage/format.rst
docs/source/usage/index.rst
docs/source/usage/installation.rst
docs/source/usage/usage_example.rst
tde/__init__.py
tde/eval.py
tde/utils.py
tde/measures/__init__.py
tde/measures/boundary.py
tde/measures/coverage.py
tde/measures/grouping.py
tde/measures/measures.py
tde/measures/ned.py
tde/measures/token_type.py
tde/readers/__init__.py
tde/readers/disc_reader.py
tde/readers/gold_reader.py
tde/share/ZR17_mandarin.class
tde/share/__init__.py
tde/share/bad.class
tde/share/bigger_interval.class
tde/share/buckeye.phn
tde/share/buckeye.vad
tde/share/buckeye.wrd
tde/share/english.phn
tde/share/english.vad
tde/share/english.wrd
tde/share/french.phn
tde/share/french.vad
tde/share/french.wrd
tde/share/gold.class
tde/share/gold_ngrams_200_500.class
tde/share/gold_pairs.class
tde/share/gold_words_200_500ms.class
tde/share/group_clusters.class
tde/share/group_pairs.class
tde/share/kamper_mandarin.class
tde/share/mandarin.phn
tde/share/mandarin.vad
tde/share/mandarin.wrd
tde/share/test.class
tde/share/test.phn
tde/share/test.wrd
tde/share/test_pairs
test/conftest.py
test/test_boundary.py
test/test_coverage.py
test/test_disc_reader.py
test/test_gold_reader.py
test/test_grouping.py
test/test_ned.py
test/test_token_type.py
zerospeech_tde.egg-info/PKG-INFO
zerospeech_tde.egg-info/SOURCES.txt
zerospeech_tde.egg-info/dependency_links.txt
zerospeech_tde.egg-info/requires.txt
zerospeech_tde.egg-info/top_level.txt