Metadata-Version: 2.1
Name: zerospeech-tde
Version: 2.0.3
Summary: Evaluation toolbox for Term Discovery systems
Author-email: Julien Karadayi <julien.karadayi@inria.fr>, CoML Team <dev@zerospeech.com>
License:                     GNU GENERAL PUBLIC LICENSE
Project-URL: documentation, https://docs.cognitive-ml.fr/tde/
Project-URL: source_repository, https://github.com/bootphon/tdev2
Project-URL: zerospeech_task, https://zerospeech.com/tasks/task_2/tasks_goals/
Project-URL: zerospeech_fork, https://github.com/zerospeech/tdev2
Keywords: speech,machine-learning,challenges,research-tool,benchmark-speech,zerospeech
Classifier: Programming Language :: Python :: 3.6
Classifier: Programming Language :: Python :: 3.7
Classifier: Programming Language :: Python :: 3.8
Classifier: Programming Language :: Python :: 3.9
Classifier: Programming Language :: Python :: 3.10
Classifier: Programming Language :: Python :: 3.11
Classifier: Topic :: Scientific/Engineering :: Artificial Intelligence
Classifier: Intended Audience :: Science/Research
Requires-Python: >=3.6
Provides-Extra: dev
License-File: LICENSE.txt
